LICENSE
MANIFEST.in
README.md
requirements.txt
setup.py
ansible_dynamic_inventory/__init__.py
ansible_dynamic_inventory/__version__.txt
ansible_dynamic_inventory/ansible_dynamic_inventory.ini
ansible_dynamic_inventory/cli.py
ansible_dynamic_inventory.egg-info/PKG-INFO
ansible_dynamic_inventory.egg-info/SOURCES.txt
ansible_dynamic_inventory.egg-info/dependency_links.txt
ansible_dynamic_inventory.egg-info/entry_points.txt
ansible_dynamic_inventory.egg-info/requires.txt
ansible_dynamic_inventory.egg-info/top_level.txt