Metadata-Version: 1.1
Name: ansible-dynamic-inventory
Version: 0.3.2
Summary: A command line interface for Slack
Home-page: https://github.com/Yoshiyuki-Nakahara          /python-ansible-dynamic-inventory
Author: Yoshiyuki-Nakahara
Author-email: president.hanage@gmail.com
License: MIT
Keywords: ansible dynamic inventory consul
Platform: UNKNOWN
Classifier: Development Status :: 4 - Beta
Classifier: License :: OSI Approved :: MIT License
Classifier: Programming Language :: Python :: 2.7
